{
  "m_GameObject": {
    "m_FileID": 0,
    "m_PathID": 0
  },
  "m_Enabled": 1,
  "m_Script": {
    "m_FileID": 1,
    "m_PathID": -2378050947708348859
  },
  "m_Name": "Shop_th",
  "m_LocaleId": {
    "m_Code": "th"
  },
  "m_SharedData": {
    "m_FileID": 2,
    "m_PathID": 4340967918322402021
  },
  "m_Metadata": {
    "m_Items": []
  },
  "m_TableData": [
    {
      "m_Id": 207412195328,
      "m_Localized": "ร้านค้า",
      "m_Metadata": {
        "m_Items": []
      }
    },
    {
      "m_Id": 302685810688,
      "m_Localized": "ดีลประจำวัน",
      "m_Metadata": {
        "m_Items": []
      }
    },
    {
      "m_Id": 522211487744,
      "m_Localized": "ทรัพยากร",
      "m_Metadata": {
        "m_Items": []
      }
    },
    {
      "m_Id": 698598748160,
      "m_Localized": "กลับมาดูดีลเพิ่มเติมในวันพรุ่งนี้!",
      "m_Metadata": {
        "m_Items": []
      }
    },
    {
      "m_Id": 1065419993088,
      "m_Localized": "เติมค้อน!",
      "m_Metadata": {
        "m_Items": []
      }
    },
    {
      "m_Id": 1163478626304,
      "m_Localized": "เติม",
      "m_Metadata": {
        "m_Items": []
      }
    },
    {
      "m_Id": 3485185273856,
      "m_Localized": "ดีล",
      "m_Metadata": {
        "m_Items": []
      }
    },
    {
      "m_Id": 3485185273857,
      "m_Localized": "ข้อเสนอ",
      "m_Metadata": {
        "m_Items": []
      }
    },
    {
      "m_Id": 4701478907904,
      "m_Localized": "ดันเจี้ยน",
      "m_Metadata": {
        "m_Items": []
      }
    },
    {
      "m_Id": 4701483102208,
      "m_Localized": "ทรัพยากร",
      "m_Metadata": {
        "m_Items": []
      }
    },
    {
      "m_Id": 4701483102209,
      "m_Localized": "สัตว์เลี้ยง",
      "m_Metadata": {
        "m_Items": []
      }
    },
    {
      "m_Id": 4701483102210,
      "m_Localized": "สกิล",
      "m_Metadata": {
        "m_Items": []
      }
    },
    {
      "m_Id": 4701483102211,
      "m_Localized": "เทค",
      "m_Metadata": {
        "m_Items": []
      }
    },
    {
      "m_Id": 22473983646490624,
      "m_Localized": "สัตว์พาหนะ",
      "m_Metadata": {
        "m_Items": []
      }
    },
    {
      "m_Id": 27127988465164288,
      "m_Localized": "ซื้อดีลประจำวันทั้งสามรายการเพื่อรับสามรายการใหม่!",
      "m_Metadata": {
        "m_Items": []
      }
    },
    {
      "m_Id": 53302178176032768,
      "m_Localized": "โทเค็นกระโดดหิน",
      "m_Metadata": {
        "m_Items": []
      }
    }
  ],
  "references": {
    "version": 2,
    "RefIds": []
  }
}