{
  "m_GameObject": {
    "m_FileID": 0,
    "m_PathID": 0
  },
  "m_Enabled": 1,
  "m_Script": {
    "m_FileID": 1,
    "m_PathID": -2378050947708348859
  },
  "m_Name": "Skills_th",
  "m_LocaleId": {
    "m_Code": "th"
  },
  "m_SharedData": {
    "m_FileID": 2,
    "m_PathID": -3517678328824788358
  },
  "m_Metadata": {
    "m_Items": []
  },
  "m_TableData": [
    {
      "m_Id": 208976670720,
      "m_Localized": "เนื้อ",
      "m_Metadata": {
        "m_Items": []
      }
    },
    {
      "m_Id": 216287342592,
      "m_Localized": "ขวัญกำลังใจ",
      "m_Metadata": {
        "m_Items": []
      }
    },
    {
      "m_Id": 233735647232,
      "m_Localized": "ลูกธนู",
      "m_Metadata": {
        "m_Items": []
      }
    },
    {
      "m_Id": 247690096640,
      "m_Localized": "ตะโกน",
      "m_Metadata": {
        "m_Items": []
      }
    },
    {
      "m_Id": 264307929088,
      "m_Localized": "อุกกาบาต",
      "m_Metadata": {
        "m_Items": []
      }
    },
    {
      "m_Id": 288559394816,
      "m_Localized": "บ้าคลั่ง",
      "m_Metadata": {
        "m_Items": []
      }
    },
    {
      "m_Id": 306217414656,
      "m_Localized": "ฝูงสัตว์บุก",
      "m_Metadata": {
        "m_Items": []
      }
    },
    {
      "m_Id": 321933471744,
      "m_Localized": "หนาม",
      "m_Metadata": {
        "m_Items": []
      }
    },
    {
      "m_Id": 338651967488,
      "m_Localized": "ระเบิด",
      "m_Metadata": {
        "m_Items": []
      }
    },
    {
      "m_Id": 356767166464,
      "m_Localized": "หนอนยักษ์",
      "m_Metadata": {
        "m_Items": []
      }
    },
    {
      "m_Id": 430301704192,
      "m_Localized": "สายฟ้า",
      "m_Metadata": {
        "m_Items": []
      }
    },
    {
      "m_Id": 446353305600,
      "m_Localized": "บัฟ",
      "m_Metadata": {
        "m_Items": []
      }
    },
    {
      "m_Id": 460181925888,
      "m_Localized": "ขวัญกำลังใจสูงขึ้น",
      "m_Metadata": {
        "m_Items": []
      }
    },
    {
      "m_Id": 503324536832,
      "m_Localized": "ฝนธนู",
      "m_Metadata": {
        "m_Items": []
      }
    },
    {
      "m_Id": 640000126976,
      "m_Localized": "กินเนื้อสักหน่อยและเพิ่มพลังชีวิตของคุณ {0} เป็นเวลา {1} วินาที",
      "m_Metadata": {
        "m_Items": []
      }
    },
    {
      "m_Id": 996302057472,
      "m_Localized": "ได้รับแรงบันดาลใจและเพิ่มความเสียหาย {0} และพลังชีวิต {1} เป็นเวลา {2} วินาที",
      "m_Metadata": {
        "m_Items": []
      }
    },
    {
      "m_Id": 1018934521856,
      "m_Localized": "เรียกฝูงลูกธนู แต่ละลูกสร้างความเสียหาย {0}",
      "m_Metadata": {
        "m_Items": []
      }
    },
    {
      "m_Id": 1055152336896,
      "m_Localized": "ให้เพื่อนนินจาของคุณขว้างชูริเก็น แต่ละอันสร้างความเสียหาย {0}",
      "m_Metadata": {
        "m_Items": []
      }
    },
    {
      "m_Id": 1093542801408,
      "m_Localized": "ส่งเสียงตะโกนสนั่นหวั่นไหว สร้างความเสียหาย {0} ให้ศัตรูทั้งหมด",
      "m_Metadata": {
        "m_Items": []
      }
    },
    {
      "m_Id": 1132528857088,
      "m_Localized": "เรียกอุกกาบาตหนึ่งคลื่นลงมา แต่ละลูกสร้างความเสียหาย {0}",
      "m_Metadata": {
        "m_Items": []
      }
    },
    {
      "m_Id": 1158541930496,
      "m_Localized": "เข้าสู่โหมดบ้าคลั่งและเพิ่มความเสียหาย {0} เป็นเวลา {1} วินาที",
      "m_Metadata": {
        "m_Items": []
      }
    },
    {
      "m_Id": 1200103288832,
      "m_Localized": "เรียกการพุ่งชน แต่ละครั้งสร้างความเสียหาย {0}",
      "m_Metadata": {
        "m_Items": []
      }
    },
    {
      "m_Id": 1263252729856,
      "m_Localized": "ปลูกหนามบนสนามรบ สร้างความเสียหาย {0} ให้ศัตรูทั้งหมด",
      "m_Metadata": {
        "m_Items": []
      }
    },
    {
      "m_Id": 1304310771712,
      "m_Localized": "ทิ้งระเบิดลงบนสนามรบ สร้างความเสียหาย {0} ให้ศัตรูทั้งหมด",
      "m_Metadata": {
        "m_Items": []
      }
    },
    {
      "m_Id": 1334736252928,
      "m_Localized": "เรียกหนอนยักษ์ที่สร้างความเสียหาย {0} ให้ศัตรูทั้งหมด",
      "m_Metadata": {
        "m_Items": []
      }
    },
    {
      "m_Id": 1369259569152,
      "m_Localized": "เรียกสายฟ้า แต่ละสายสร้างความเสียหาย {0} ให้ศัตรูทั้งหมด",
      "m_Metadata": {
        "m_Items": []
      }
    },
    {
      "m_Id": 1406169444352,
      "m_Localized": "บัฟตัวเอง เพิ่มความเสียหาย {0} และพลังชีวิต {1} เป็นเวลา {2} วินาที",
      "m_Metadata": {
        "m_Items": []
      }
    },
    {
      "m_Id": 1429477191680,
      "m_Localized": "ได้รับแรงบันดาลใจจากเทพ เพิ่มความเสียหาย {0} และพลังชีวิต {1} เป็นเวลา {2} วินาที",
      "m_Metadata": {
        "m_Items": []
      }
    },
    {
      "m_Id": 1468731682816,
      "m_Localized": "ทำให้ฝนธนูตกลงมา สร้างความเสียหาย {0}",
      "m_Metadata": {
        "m_Items": []
      }
    },
    {
      "m_Id": 1711400141123584,
      "m_Localized": "ชูริเก็น",
      "m_Metadata": {
        "m_Items": []
      }
    },
    {
      "m_Id": 1711400170483712,
      "m_Localized": "บินกราดยิง",
      "m_Metadata": {
        "m_Items": []
      }
    },
    {
      "m_Id": 1711400170483713,
      "m_Localized": "เรียกการสนับสนุนทางอากาศหนัก สร้างความเสียหาย {0}",
      "m_Metadata": {
        "m_Items": []
      }
    },
    {
      "m_Id": 1711400170483714,
      "m_Localized": "ปืนใหญ่ระดมยิง",
      "m_Metadata": {
        "m_Items": []
      }
    },
    {
      "m_Id": 1711400170483715,
      "m_Localized": "ยิงลูกปืนใหญ่ถล่ม แต่ละลูกสร้างความเสียหาย {0}",
      "m_Metadata": {
        "m_Items": []
      }
    },
    {
      "m_Id": 1711400170483716,
      "m_Localized": "โดรน",
      "m_Metadata": {
        "m_Items": []
      }
    },
    {
      "m_Id": 1711400170483717,
      "m_Localized": "เรียกโดรนมาต่อสู้เคียงข้างคุณ สร้างความเสียหาย {0} เป็นเวลา {1} วินาที",
      "m_Metadata": {
        "m_Items": []
      }
    },
    {
      "m_Id": 2058764945125376,
      "m_Localized": "อัตโนมัติ เปิด",
      "m_Metadata": {
        "m_Items": []
      }
    },
    {
      "m_Id": 2058764974485504,
      "m_Localized": "อัตโนมัติ ปิด",
      "m_Metadata": {
        "m_Items": []
      }
    },
    {
      "m_Id": 2060633843101696,
      "m_Localized": "เรียก",
      "m_Metadata": {
        "m_Items": []
      }
    },
    {
      "m_Id": 2060633843101697,
      "m_Localized": "พื้นฐาน",
      "m_Metadata": {
        "m_Items": []
      }
    },
    {
      "m_Id": 2061927358066688,
      "m_Localized": "อัปเกรดทั้งหมด",
      "m_Metadata": {
        "m_Items": []
      }
    },
    {
      "m_Id": 2061927358066689,
      "m_Localized": "ติดตั้งเร็ว",
      "m_Metadata": {
        "m_Items": []
      }
    },
    {
      "m_Id": 3898839411974144,
      "m_Localized": "พาสซีฟ:",
      "m_Metadata": {
        "m_Items": []
      }
    }
  ],
  "references": {
    "version": 2,
    "RefIds": []
  }
}