{
  "m_GameObject": {
    "m_FileID": 0,
    "m_PathID": 0
  },
  "m_Enabled": 1,
  "m_Script": {
    "m_FileID": 1,
    "m_PathID": -2378050947708348859
  },
  "m_Name": "TechTree_zh-TW",
  "m_LocaleId": {
    "m_Code": "zh-TW"
  },
  "m_SharedData": {
    "m_FileID": 2,
    "m_PathID": 3510350058130572738
  },
  "m_Metadata": {
    "m_Items": []
  },
  "m_TableData": [
    {
      "m_Id": 55555327238144,
      "m_Localized": "武器精通",
      "m_Metadata": {
        "m_Items": []
      }
    },
    {
      "m_Id": 55555335626752,
      "m_Localized": "頭盔精通",
      "m_Metadata": {
        "m_Items": []
      }
    },
    {
      "m_Id": 55555339821056,
      "m_Localized": "身體精通",
      "m_Metadata": {
        "m_Items": []
      }
    },
    {
      "m_Id": 55555339821057,
      "m_Localized": "鞋子精通",
      "m_Metadata": {
        "m_Items": []
      }
    },
    {
      "m_Id": 55555339821058,
      "m_Localized": "手套精通",
      "m_Metadata": {
        "m_Items": []
      }
    },
    {
      "m_Id": 55555339821059,
      "m_Localized": "腰帶精通",
      "m_Metadata": {
        "m_Items": []
      }
    },
    {
      "m_Id": 55555339821060,
      "m_Localized": "項鍊精通",
      "m_Metadata": {
        "m_Items": []
      }
    },
    {
      "m_Id": 55555339821061,
      "m_Localized": "戒指精通",
      "m_Metadata": {
        "m_Items": []
      }
    },
    {
      "m_Id": 55555339821062,
      "m_Localized": "武器升級",
      "m_Metadata": {
        "m_Items": []
      }
    },
    {
      "m_Id": 55555339821063,
      "m_Localized": "頭盔升級",
      "m_Metadata": {
        "m_Items": []
      }
    },
    {
      "m_Id": 55555339821064,
      "m_Localized": "身體升級",
      "m_Metadata": {
        "m_Items": []
      }
    },
    {
      "m_Id": 55555339821065,
      "m_Localized": "鞋子升級",
      "m_Metadata": {
        "m_Items": []
      }
    },
    {
      "m_Id": 55555339821066,
      "m_Localized": "手套升級",
      "m_Metadata": {
        "m_Items": []
      }
    },
    {
      "m_Id": 55555339821067,
      "m_Localized": "腰帶升級",
      "m_Metadata": {
        "m_Items": []
      }
    },
    {
      "m_Id": 55555339821068,
      "m_Localized": "項鍊升級",
      "m_Metadata": {
        "m_Items": []
      }
    },
    {
      "m_Id": 55555339821069,
      "m_Localized": "戒指升級",
      "m_Metadata": {
        "m_Items": []
      }
    },
    {
      "m_Id": 58664321523712,
      "m_Localized": "坐騎傷害精通",
      "m_Metadata": {
        "m_Items": []
      }
    },
    {
      "m_Id": 58664325718016,
      "m_Localized": "坐騎生命精通",
      "m_Metadata": {
        "m_Items": []
      }
    },
    {
      "m_Id": 58664325718017,
      "m_Localized": "額外坐騎機率",
      "m_Metadata": {
        "m_Items": []
      }
    },
    {
      "m_Id": 58664325718018,
      "m_Localized": "坐騎召喚成本",
      "m_Metadata": {
        "m_Items": []
      }
    },
    {
      "m_Id": 55555339821073,
      "m_Localized": "鍛造計時器",
      "m_Metadata": {
        "m_Items": []
      }
    },
    {
      "m_Id": 55555339821074,
      "m_Localized": "鍛造升級成本",
      "m_Metadata": {
        "m_Items": []
      }
    },
    {
      "m_Id": 55555339821075,
      "m_Localized": "裝備出售價格",
      "m_Metadata": {
        "m_Items": []
      }
    },
    {
      "m_Id": 55555339821076,
      "m_Localized": "自動鍛造",
      "m_Metadata": {
        "m_Items": []
      }
    },
    {
      "m_Id": 55555339821077,
      "m_Localized": "鎚子離線獎勵",
      "m_Metadata": {
        "m_Items": []
      }
    },
    {
      "m_Id": 55555339821078,
      "m_Localized": "金幣離線獎勵",
      "m_Metadata": {
        "m_Items": []
      }
    },
    {
      "m_Id": 55555339821079,
      "m_Localized": "最大離線時間",
      "m_Metadata": {
        "m_Items": []
      }
    },
    {
      "m_Id": 55555339821080,
      "m_Localized": "免費鍛造機率",
      "m_Metadata": {
        "m_Items": []
      }
    },
    {
      "m_Id": 55555339821081,
      "m_Localized": "錘子小偷鎚子加成",
      "m_Metadata": {
        "m_Items": []
      }
    },
    {
      "m_Id": 55555339821082,
      "m_Localized": "錘子小偷金幣加成",
      "m_Metadata": {
        "m_Items": []
      }
    },
    {
      "m_Id": 55555339821083,
      "m_Localized": "技能傷害精通",
      "m_Metadata": {
        "m_Items": []
      }
    },
    {
      "m_Id": 55555339821084,
      "m_Localized": "技能被動傷害",
      "m_Metadata": {
        "m_Items": []
      }
    },
    {
      "m_Id": 55555339821085,
      "m_Localized": "技能被動生命",
      "m_Metadata": {
        "m_Items": []
      }
    },
    {
      "m_Id": 55555339821086,
      "m_Localized": "鬼鎮技能券加成",
      "m_Metadata": {
        "m_Items": []
      }
    },
    {
      "m_Id": 55555339821087,
      "m_Localized": "技能召喚成本",
      "m_Metadata": {
        "m_Items": []
      }
    },
    {
      "m_Id": 55555339821088,
      "m_Localized": "寵物傷害精通",
      "m_Metadata": {
        "m_Items": []
      }
    },
    {
      "m_Id": 55555339821089,
      "m_Localized": "寵物生命精通",
      "m_Metadata": {
        "m_Items": []
      }
    },
    {
      "m_Id": 55555339821090,
      "m_Localized": "額外蛋機率",
      "m_Metadata": {
        "m_Items": []
      }
    },
    {
      "m_Id": 55555339821091,
      "m_Localized": "普通蛋計時器",
      "m_Metadata": {
        "m_Items": []
      }
    },
    {
      "m_Id": 55555339821092,
      "m_Localized": "稀有蛋計時器",
      "m_Metadata": {
        "m_Items": []
      }
    },
    {
      "m_Id": 55555339821093,
      "m_Localized": "史詩蛋計時器",
      "m_Metadata": {
        "m_Items": []
      }
    },
    {
      "m_Id": 55555339821094,
      "m_Localized": "傳奇蛋計時器",
      "m_Metadata": {
        "m_Items": []
      }
    },
    {
      "m_Id": 55555339821095,
      "m_Localized": "終極蛋計時器",
      "m_Metadata": {
        "m_Items": []
      }
    },
    {
      "m_Id": 55555339821096,
      "m_Localized": "神話蛋計時器",
      "m_Metadata": {
        "m_Items": []
      }
    },
    {
      "m_Id": 55555339821097,
      "m_Localized": "殭屍狂奔科技藥水加成",
      "m_Metadata": {
        "m_Items": []
      }
    },
    {
      "m_Id": 55555339821098,
      "m_Localized": "科技節點升級成本",
      "m_Metadata": {
        "m_Items": []
      }
    },
    {
      "m_Id": 55555339821099,
      "m_Localized": "科技研究計時器",
      "m_Metadata": {
        "m_Items": []
      }
    },
    {
      "m_Id": 55555339821100,
      "m_Localized": "武器加成傷害 {0}",
      "m_Metadata": {
        "m_Items": []
      }
    },
    {
      "m_Id": 55555339821101,
      "m_Localized": "頭盔加成生命 {0}",
      "m_Metadata": {
        "m_Items": []
      }
    },
    {
      "m_Id": 55555339821102,
      "m_Localized": "身體加成生命 {0}",
      "m_Metadata": {
        "m_Items": []
      }
    },
    {
      "m_Id": 55555339821103,
      "m_Localized": "鞋子加成生命 {0}",
      "m_Metadata": {
        "m_Items": []
      }
    },
    {
      "m_Id": 55555339821104,
      "m_Localized": "手套加成傷害 {0}",
      "m_Metadata": {
        "m_Items": []
      }
    },
    {
      "m_Id": 55555339821105,
      "m_Localized": "腰帶加成生命 {0}",
      "m_Metadata": {
        "m_Items": []
      }
    },
    {
      "m_Id": 55555339821106,
      "m_Localized": "項鍊加成傷害 {0}",
      "m_Metadata": {
        "m_Items": []
      }
    },
    {
      "m_Id": 55555339821107,
      "m_Localized": "戒指加成傷害 {0}",
      "m_Metadata": {
        "m_Items": []
      }
    },
    {
      "m_Id": 55555339821108,
      "m_Localized": "武器最高等級 {0}",
      "m_Metadata": {
        "m_Items": []
      }
    },
    {
      "m_Id": 55555339821109,
      "m_Localized": "頭盔最高等級 {0}",
      "m_Metadata": {
        "m_Items": []
      }
    },
    {
      "m_Id": 55555339821110,
      "m_Localized": "身體最高等級 {0}",
      "m_Metadata": {
        "m_Items": []
      }
    },
    {
      "m_Id": 55555339821111,
      "m_Localized": "鞋子最高等級 {0}",
      "m_Metadata": {
        "m_Items": []
      }
    },
    {
      "m_Id": 55555339821112,
      "m_Localized": "手套最高等級 {0}",
      "m_Metadata": {
        "m_Items": []
      }
    },
    {
      "m_Id": 55555339821113,
      "m_Localized": "腰帶最高等級 {0}",
      "m_Metadata": {
        "m_Items": []
      }
    },
    {
      "m_Id": 55555339821114,
      "m_Localized": "項鍊最高等級 {0}",
      "m_Metadata": {
        "m_Items": []
      }
    },
    {
      "m_Id": 55555339821115,
      "m_Localized": "戒指最高等級 {0}",
      "m_Metadata": {
        "m_Items": []
      }
    },
    {
      "m_Id": 55555339821116,
      "m_Localized": "坐騎加成傷害 {0}",
      "m_Metadata": {
        "m_Items": []
      }
    },
    {
      "m_Id": 55555339821117,
      "m_Localized": "坐騎加成生命 {0}",
      "m_Metadata": {
        "m_Items": []
      }
    },
    {
      "m_Id": 55555339821118,
      "m_Localized": "升級坐騎時的加成經驗值 {0}",
      "m_Metadata": {
        "m_Items": []
      }
    },
    {
      "m_Id": 58664325718019,
      "m_Localized": "坐騎召喚成本 {0}",
      "m_Metadata": {
        "m_Items": []
      }
    },
    {
      "m_Id": 55555339821119,
      "m_Localized": "鍛造升級計時器速度 {0}",
      "m_Metadata": {
        "m_Items": []
      }
    },
    {
      "m_Id": 55555339821120,
      "m_Localized": "鍛造升級成本 {0}",
      "m_Metadata": {
        "m_Items": []
      }
    },
    {
      "m_Id": 55555339821121,
      "m_Localized": "裝備出售價格 {0}",
      "m_Metadata": {
        "m_Items": []
      }
    },
    {
      "m_Id": 55555339821122,
      "m_Localized": "一次使用的鎚子數量 {0}",
      "m_Metadata": {
        "m_Items": []
      }
    },
    {
      "m_Id": 55555339821123,
      "m_Localized": "鎚子離線獎勵加成 {0}",
      "m_Metadata": {
        "m_Items": []
      }
    },
    {
      "m_Id": 55555339821124,
      "m_Localized": "金幣離線獎勵加成 {0}",
      "m_Metadata": {
        "m_Items": []
      }
    },
    {
      "m_Id": 55555339821125,
      "m_Localized": "最大離線獎勵時間 {0}",
      "m_Metadata": {
        "m_Items": []
      }
    },
    {
      "m_Id": 55555339821126,
      "m_Localized": "免費鍛造裝備的機率 {0}",
      "m_Metadata": {
        "m_Items": []
      }
    },
    {
      "m_Id": 55555339821127,
      "m_Localized": "錘子小偷地下城多掉落 {0} 個鎚子",
      "m_Metadata": {
        "m_Items": []
      }
    },
    {
      "m_Id": 55555339821128,
      "m_Localized": "錘子小偷地下城多掉落 {0} 個金幣",
      "m_Metadata": {
        "m_Items": []
      }
    },
    {
      "m_Id": 55555339821129,
      "m_Localized": "技能傷害 {0}",
      "m_Metadata": {
        "m_Items": []
      }
    },
    {
      "m_Id": 55555339821130,
      "m_Localized": "技能被動基礎傷害 {0}",
      "m_Metadata": {
        "m_Items": []
      }
    },
    {
      "m_Id": 55555339821131,
      "m_Localized": "技能被動基礎生命 {0}",
      "m_Metadata": {
        "m_Items": []
      }
    },
    {
      "m_Id": 55555339821132,
      "m_Localized": "鬼鎮地下城多掉落 {0} 張技能券",
      "m_Metadata": {
        "m_Items": []
      }
    },
    {
      "m_Id": 55555339821133,
      "m_Localized": "技能召喚成本 {0}",
      "m_Metadata": {
        "m_Items": []
      }
    },
    {
      "m_Id": 55555339821134,
      "m_Localized": "寵物加成傷害 {0}",
      "m_Metadata": {
        "m_Items": []
      }
    },
    {
      "m_Id": 55555339821135,
      "m_Localized": "寵物加成生命 {0}",
      "m_Metadata": {
        "m_Items": []
      }
    },
    {
      "m_Id": 55555339821136,
      "m_Localized": "升級寵物時的加成經驗值 {0}",
      "m_Metadata": {
        "m_Items": []
      }
    },
    {
      "m_Id": 55555339821137,
      "m_Localized": "普通蛋孵化計時器速度 {0}",
      "m_Metadata": {
        "m_Items": []
      }
    },
    {
      "m_Id": 55555339821138,
      "m_Localized": "稀有蛋孵化計時器速度 {0}",
      "m_Metadata": {
        "m_Items": []
      }
    },
    {
      "m_Id": 55555339821139,
      "m_Localized": "史詩蛋孵化計時器速度 {0}",
      "m_Metadata": {
        "m_Items": []
      }
    },
    {
      "m_Id": 55555339821140,
      "m_Localized": "傳奇蛋孵化計時器速度 {0}",
      "m_Metadata": {
        "m_Items": []
      }
    },
    {
      "m_Id": 55555339821141,
      "m_Localized": "終極蛋孵化計時器速度 {0}",
      "m_Metadata": {
        "m_Items": []
      }
    },
    {
      "m_Id": 55555339821142,
      "m_Localized": "神話蛋孵化計時器速度 {0}",
      "m_Metadata": {
        "m_Items": []
      }
    },
    {
      "m_Id": 55555339821143,
      "m_Localized": "殭屍狂奔地下城多掉落 {0} 個科技藥水",
      "m_Metadata": {
        "m_Items": []
      }
    },
    {
      "m_Id": 55555339821144,
      "m_Localized": "科技節點升級成本 {0}",
      "m_Metadata": {
        "m_Items": []
      }
    },
    {
      "m_Id": 55555339821145,
      "m_Localized": "科技研究計時器速度 {0}",
      "m_Metadata": {
        "m_Items": []
      }
    },
    {
      "m_Id": 280318681088,
      "m_Localized": "科技樹",
      "m_Metadata": {
        "m_Items": []
      }
    },
    {
      "m_Id": 280343846912,
      "m_Localized": "鍛造",
      "m_Metadata": {
        "m_Items": []
      }
    },
    {
      "m_Id": 280343846913,
      "m_Localized": "力量",
      "m_Metadata": {
        "m_Items": []
      }
    },
    {
      "m_Id": 280343846914,
      "m_Localized": "技能、寵物與科技",
      "m_Metadata": {
        "m_Items": []
      }
    },
    {
      "m_Id": 17687817399296000,
      "m_Localized": "已有另一項科技正在研究中！",
      "m_Metadata": {
        "m_Items": []
      }
    },
    {
      "m_Id": 17688556561489920,
      "m_Localized": "已滿",
      "m_Metadata": {
        "m_Items": []
      }
    },
    {
      "m_Id": 17690949319647232,
      "m_Localized": "研究中....",
      "m_Metadata": {
        "m_Items": []
      }
    },
    {
      "m_Id": 21246931924672512,
      "m_Localized": "你的科技樹升級已完成！",
      "m_Metadata": {
        "m_Items": []
      }
    },
    {
      "m_Id": 103966219382546432,
      "m_Localized": "氏族",
      "m_Metadata": {
        "m_Items": []
      }
    }
  ],
  "references": {
    "version": 2,
    "RefIds": []
  }
}